{"model.embed_tokens.weight": 0.0038285259449291147, "model.layers.0.self_attn.q_proj.weight": 0.007073640823364258, "model.layers.0.self_attn.q_proj.bias": 0.025390625, "model.layers.0.self_attn.k_proj.weight": 0.0052490234375, "model.layers.0.self_attn.k_proj.bias": 0.03515625, "model.layers.0.self_attn.v_proj.weight": 0.005039215087890625, "model.layers.0.self_attn.v_proj.bias": 0.0078125, "model.layers.0.self_attn.o_proj.weight": 0.008510112762451172, "model.layers.0.mlp.gate_proj.weight": 0.004886139270871184, "model.layers.0.mlp.up_proj.weight": 0.003988532132880632, "model.layers.0.mlp.down_proj.weight": 0.004242076430209848, "model.layers.0.input_layernorm.weight": 0.01708984375, "model.layers.0.post_attention_layernorm.weight": 0.01220703125, "model.layers.1.self_attn.q_proj.weight": 0.008550643920898438, "model.layers.1.self_attn.q_proj.bias": 0.017578125, "model.layers.1.self_attn.k_proj.weight": 0.00914764404296875, "model.layers.1.self_attn.k_proj.bias": 0.01953125, "model.layers.1.self_attn.v_proj.weight": 0.005115509033203125, "model.layers.1.self_attn.v_proj.bias": 0.0078125, "model.layers.1.self_attn.o_proj.weight": 0.005265951156616211, "model.layers.1.mlp.gate_proj.weight": 0.03368479706520258, "model.layers.1.mlp.up_proj.weight": 0.027495983035065407, "model.layers.1.mlp.down_proj.weight": 0.03060247731763263, "model.layers.1.input_layernorm.weight": 0.0087890625, "model.layers.1.post_attention_layernorm.weight": 0.0078125, "model.layers.2.self_attn.q_proj.weight": 0.008385658264160156, "model.layers.2.self_attn.q_proj.bias": 0.01708984375, "model.layers.2.self_attn.k_proj.weight": 0.00919342041015625, "model.layers.2.self_attn.k_proj.bias": 0.0234375, "model.layers.2.self_attn.v_proj.weight": 0.0041637420654296875, "model.layers.2.self_attn.v_proj.bias": 0.01953125, "model.layers.2.self_attn.o_proj.weight": 0.005297422409057617, "model.layers.2.mlp.gate_proj.weight": 0.033039980156477106, "model.layers.2.mlp.up_proj.weight": 0.03300276467966479, "model.layers.2.mlp.down_proj.weight": 0.03156843850778979, "model.layers.2.input_layernorm.weight": 0.009765625, "model.layers.2.post_attention_layernorm.weight": 0.0166015625, "model.layers.3.self_attn.q_proj.weight": 0.006920576095581055, "model.layers.3.self_attn.q_proj.bias": 0.03369140625, "model.layers.3.self_attn.k_proj.weight": 0.00791168212890625, "model.layers.3.self_attn.k_proj.bias": 0.015625, "model.layers.3.self_attn.v_proj.weight": 0.00390625, "model.layers.3.self_attn.v_proj.bias": 0.03125, "model.layers.3.self_attn.o_proj.weight": 0.004724264144897461, "model.layers.3.mlp.gate_proj.weight": 0.023393941480059955, "model.layers.3.mlp.up_proj.weight": 0.02483838103538336, "model.layers.3.mlp.down_proj.weight": 0.023050175156704215, "model.layers.3.input_layernorm.weight": 0.05859375, "model.layers.3.post_attention_layernorm.weight": 0.0126953125, "model.layers.4.self_attn.q_proj.weight": 0.008398771286010742, "model.layers.4.self_attn.q_proj.bias": 0.02880859375, "model.layers.4.self_attn.k_proj.weight": 0.008953094482421875, "model.layers.4.self_attn.k_proj.bias": 0.01953125, "model.layers.4.self_attn.v_proj.weight": 0.0042705535888671875, "model.layers.4.self_attn.v_proj.bias": 0.0078125, "model.layers.4.self_attn.o_proj.weight": 0.005469083786010742, "model.layers.4.mlp.gate_proj.weight": 0.021274211794831032, "model.layers.4.mlp.up_proj.weight": 0.021872276483580123, "model.layers.4.mlp.down_proj.weight": 0.02025040914846021, "model.layers.4.input_layernorm.weight": 0.02197265625, "model.layers.4.post_attention_layernorm.weight": 0.013671875, "model.layers.5.self_attn.q_proj.weight": 0.011617898941040039, "model.layers.5.self_attn.q_proj.bias": 0.025390625, "model.layers.5.self_attn.k_proj.weight": 0.012426376342773438, "model.layers.5.self_attn.k_proj.bias": 0.015625, "model.layers.5.self_attn.v_proj.weight": 0.00527191162109375, "model.layers.5.self_attn.v_proj.bias": 0.0234375, "model.layers.5.self_attn.o_proj.weight": 0.006556034088134766, "model.layers.5.mlp.gate_proj.weight": 0.009435919828193133, "model.layers.5.mlp.up_proj.weight": 0.011574102002520894, "model.layers.5.mlp.down_proj.weight": 0.009911958561387173, "model.layers.5.input_layernorm.weight": 0.02294921875, "model.layers.5.post_attention_layernorm.weight": 0.0107421875, "model.layers.6.self_attn.q_proj.weight": 0.008269786834716797, "model.layers.6.self_attn.q_proj.bias": 0.0166015625, "model.layers.6.self_attn.k_proj.weight": 0.00714874267578125, "model.layers.6.self_attn.k_proj.bias": 0.015625, "model.layers.6.self_attn.v_proj.weight": 0.008867263793945312, "model.layers.6.self_attn.v_proj.bias": 0.0234375, "model.layers.6.self_attn.o_proj.weight": 0.007100820541381836, "model.layers.6.mlp.gate_proj.weight": 0.00590107052825218, "model.layers.6.mlp.up_proj.weight": 0.009498684905296149, "model.layers.6.mlp.down_proj.weight": 0.007495569628338481, "model.layers.6.input_layernorm.weight": 0.02001953125, "model.layers.6.post_attention_layernorm.weight": 0.00927734375, "model.layers.7.self_attn.q_proj.weight": 0.008023262023925781, "model.layers.7.self_attn.q_proj.bias": 0.02294921875, "model.layers.7.self_attn.k_proj.weight": 0.00765228271484375, "model.layers.7.self_attn.k_proj.bias": 0.0234375, "model.layers.7.self_attn.v_proj.weight": 0.0045757293701171875, "model.layers.7.self_attn.v_proj.bias": 0.0234375, "model.layers.7.self_attn.o_proj.weight": 0.0046083927154541016, "model.layers.7.mlp.gate_proj.weight": 0.0060535253480423325, "model.layers.7.mlp.up_proj.weight": 0.008457583050395167, "model.layers.7.mlp.down_proj.weight": 0.006762526756109193, "model.layers.7.input_layernorm.weight": 0.02294921875, "model.layers.7.post_attention_layernorm.weight": 0.01123046875, "model.layers.8.self_attn.q_proj.weight": 0.006295919418334961, "model.layers.8.self_attn.q_proj.bias": 0.015625, "model.layers.8.self_attn.k_proj.weight": 0.008119583129882812, "model.layers.8.self_attn.k_proj.bias": 0.015625, "model.layers.8.self_attn.v_proj.weight": 0.0042285919189453125, "model.layers.8.self_attn.v_proj.bias": 0.0078125, "model.layers.8.self_attn.o_proj.weight": 0.004157304763793945, "model.layers.8.mlp.gate_proj.weight": 0.003599299940952035, "model.layers.8.mlp.up_proj.weight": 0.005468989527502725, "model.layers.8.mlp.down_proj.weight": 0.004666749821152798, "model.layers.8.input_layernorm.weight": 0.0146484375, "model.layers.8.post_attention_layernorm.weight": 0.0107421875, "model.layers.9.self_attn.q_proj.weight": 0.0066547393798828125, "model.layers.9.self_attn.q_proj.bias": 0.01318359375, "model.layers.9.self_attn.k_proj.weight": 0.006908416748046875, "model.layers.9.self_attn.k_proj.bias": 0.01171875, "model.layers.9.self_attn.v_proj.weight": 0.0041561126708984375, "model.layers.9.self_attn.v_proj.bias": 0.0234375, "model.layers.9.self_attn.o_proj.weight": 0.004956245422363281, "model.layers.9.mlp.gate_proj.weight": 0.004222515017487282, "model.layers.9.mlp.up_proj.weight": 0.0059026230213254, "model.layers.9.mlp.down_proj.weight": 0.0053604037262672604, "model.layers.9.input_layernorm.weight": 0.0146484375, "model.layers.9.post_attention_layernorm.weight": 0.00927734375, "model.layers.10.self_attn.q_proj.weight": 0.008535623550415039, "model.layers.10.self_attn.q_proj.bias": 0.02001953125, "model.layers.10.self_attn.k_proj.weight": 0.009714126586914062, "model.layers.10.self_attn.k_proj.bias": 0.015625, "model.layers.10.self_attn.v_proj.weight": 0.0057373046875, "model.layers.10.self_attn.v_proj.bias": 0.015625, "model.layers.10.self_attn.o_proj.weight": 0.0063517093658447266, "model.layers.10.mlp.gate_proj.weight": 0.004482136216274527, "model.layers.10.mlp.up_proj.weight": 0.004929254221361737, "model.layers.10.mlp.down_proj.weight": 0.005181334739507631, "model.layers.10.input_layernorm.weight": 0.0185546875, "model.layers.10.post_attention_layernorm.weight": 0.0078125, "model.layers.11.self_attn.q_proj.weight": 0.007630825042724609, "model.layers.11.self_attn.q_proj.bias": 0.015625, "model.layers.11.self_attn.k_proj.weight": 0.0082550048828125, "model.layers.11.self_attn.k_proj.bias": 0.015625, "model.layers.11.self_attn.v_proj.weight": 0.0050811767578125, "model.layers.11.self_attn.v_proj.bias": 0.01953125, "model.layers.11.self_attn.o_proj.weight": 0.006871938705444336, "model.layers.11.mlp.gate_proj.weight": 0.005511927050213481, "model.layers.11.mlp.up_proj.weight": 0.004239991653797238, "model.layers.11.mlp.down_proj.weight": 0.004900732705759448, "model.layers.11.input_layernorm.weight": 0.01416015625, "model.layers.11.post_attention_layernorm.weight": 0.005859375, "model.layers.12.self_attn.q_proj.weight": 0.008319377899169922, "model.layers.12.self_attn.q_proj.bias": 0.0205078125, "model.layers.12.self_attn.k_proj.weight": 0.009393692016601562, "model.layers.12.self_attn.k_proj.bias": 0.01953125, "model.layers.12.self_attn.v_proj.weight": 0.004154205322265625, "model.layers.12.self_attn.v_proj.bias": 0.0078125, "model.layers.12.self_attn.o_proj.weight": 0.0054972171783447266, "model.layers.12.mlp.gate_proj.weight": 0.005535835443541061, "model.layers.12.mlp.up_proj.weight": 0.004211203996525254, "model.layers.12.mlp.down_proj.weight": 0.004953118257744368, "model.layers.12.input_layernorm.weight": 0.0126953125, "model.layers.12.post_attention_layernorm.weight": 0.0029296875, "model.layers.13.self_attn.q_proj.weight": 0.010380029678344727, "model.layers.13.self_attn.q_proj.bias": 0.02587890625, "model.layers.13.self_attn.k_proj.weight": 0.011522293090820312, "model.layers.13.self_attn.k_proj.bias": 0.0234375, "model.layers.13.self_attn.v_proj.weight": 0.0039615631103515625, "model.layers.13.self_attn.v_proj.bias": 0.01953125, "model.layers.13.self_attn.o_proj.weight": 0.006459474563598633, "model.layers.13.mlp.gate_proj.weight": 0.004461598950763082, "model.layers.13.mlp.up_proj.weight": 0.003826451856036519, "model.layers.13.mlp.down_proj.weight": 0.004218389821607013, "model.layers.13.input_layernorm.weight": 0.0146484375, "model.layers.13.post_attention_layernorm.weight": 0.00146484375, "model.layers.14.self_attn.q_proj.weight": 0.007648944854736328, "model.layers.14.self_attn.q_proj.bias": 0.01513671875, "model.layers.14.self_attn.k_proj.weight": 0.007982254028320312, "model.layers.14.self_attn.k_proj.bias": 0.015625, "model.layers.14.self_attn.v_proj.weight": 0.0040740966796875, "model.layers.14.self_attn.v_proj.bias": 0.0078125, "model.layers.14.self_attn.o_proj.weight": 0.00561833381652832, "model.layers.14.mlp.gate_proj.weight": 0.004642176073650981, "model.layers.14.mlp.up_proj.weight": 0.003971809564634811, "model.layers.14.mlp.down_proj.weight": 0.0043716874233511996, "model.layers.14.input_layernorm.weight": 0.01220703125, "model.layers.14.post_attention_layernorm.weight": 0.00146484375, "model.layers.15.self_attn.q_proj.weight": 0.011336326599121094, "model.layers.15.self_attn.q_proj.bias": 0.0263671875, "model.layers.15.self_attn.k_proj.weight": 0.010095596313476562, "model.layers.15.self_attn.k_proj.bias": 0.01171875, "model.layers.15.self_attn.v_proj.weight": 0.0050373077392578125, "model.layers.15.self_attn.v_proj.bias": 0.01953125, "model.layers.15.self_attn.o_proj.weight": 0.0058443546295166016, "model.layers.15.mlp.gate_proj.weight": 0.004386990569358648, "model.layers.15.mlp.up_proj.weight": 0.0042024656783702765, "model.layers.15.mlp.down_proj.weight": 0.004649894182072129, "model.layers.15.input_layernorm.weight": 0.00830078125, "model.layers.15.post_attention_layernorm.weight": 0.0009765625, "model.layers.16.self_attn.q_proj.weight": 0.005754709243774414, "model.layers.16.self_attn.q_proj.bias": 0.017578125, "model.layers.16.self_attn.k_proj.weight": 0.007579803466796875, "model.layers.16.self_attn.k_proj.bias": 0.015625, "model.layers.16.self_attn.v_proj.weight": 0.0039196014404296875, "model.layers.16.self_attn.v_proj.bias": 0.015625, "model.layers.16.self_attn.o_proj.weight": 0.005407094955444336, "model.layers.16.mlp.gate_proj.weight": 0.0050956814788108646, "model.layers.16.mlp.up_proj.weight": 0.004504004190134448, "model.layers.16.mlp.down_proj.weight": 0.004748677098473837, "model.layers.16.input_layernorm.weight": 0.0048828125, "model.layers.16.post_attention_layernorm.weight": 0.00048828125, "model.layers.17.self_attn.q_proj.weight": 0.011935949325561523, "model.layers.17.self_attn.q_proj.bias": 0.02197265625, "model.layers.17.self_attn.k_proj.weight": 0.013111114501953125, "model.layers.17.self_attn.k_proj.bias": 0.0234375, "model.layers.17.self_attn.v_proj.weight": 0.006214141845703125, "model.layers.17.self_attn.v_proj.bias": 0.0078125, "model.layers.17.self_attn.o_proj.weight": 0.007848262786865234, "model.layers.17.mlp.gate_proj.weight": 0.005209412685660429, "model.layers.17.mlp.up_proj.weight": 0.004632461902707122, "model.layers.17.mlp.down_proj.weight": 0.005105129508085029, "model.layers.17.input_layernorm.weight": 0.0048828125, "model.layers.17.post_attention_layernorm.weight": 0.00048828125, "model.layers.18.self_attn.q_proj.weight": 0.00787973403930664, "model.layers.18.self_attn.q_proj.bias": 0.0185546875, "model.layers.18.self_attn.k_proj.weight": 0.008539199829101562, "model.layers.18.self_attn.k_proj.bias": 0.01171875, "model.layers.18.self_attn.v_proj.weight": 0.00421905517578125, "model.layers.18.self_attn.v_proj.bias": 0.01171875, "model.layers.18.self_attn.o_proj.weight": 0.0058135986328125, "model.layers.18.mlp.gate_proj.weight": 0.006241155225177144, "model.layers.18.mlp.up_proj.weight": 0.0046980214673419335, "model.layers.18.mlp.down_proj.weight": 0.0052409948304642075, "model.layers.18.input_layernorm.weight": 0.00146484375, "model.layers.18.post_attention_layernorm.weight": 0.00048828125, "model.layers.19.self_attn.q_proj.weight": 0.013036489486694336, "model.layers.19.self_attn.q_proj.bias": 0.0283203125, "model.layers.19.self_attn.k_proj.weight": 0.013103485107421875, "model.layers.19.self_attn.k_proj.bias": 0.01171875, "model.layers.19.self_attn.v_proj.weight": 0.00577545166015625, "model.layers.19.self_attn.v_proj.bias": 0.0234375, "model.layers.19.self_attn.o_proj.weight": 0.008878231048583984, "model.layers.19.mlp.gate_proj.weight": 0.0059053287949672965, "model.layers.19.mlp.up_proj.weight": 0.005201295364734738, "model.layers.19.mlp.down_proj.weight": 0.0055452391158702765, "model.layers.19.input_layernorm.weight": 0.00146484375, "model.layers.19.post_attention_layernorm.weight": 0.00048828125, "model.layers.20.self_attn.q_proj.weight": 0.011798620223999023, "model.layers.20.self_attn.q_proj.bias": 0.0302734375, "model.layers.20.self_attn.k_proj.weight": 0.017663955688476562, "model.layers.20.self_attn.k_proj.bias": 0.0078125, "model.layers.20.self_attn.v_proj.weight": 0.009876251220703125, "model.layers.20.self_attn.v_proj.bias": 0.01171875, "model.layers.20.self_attn.o_proj.weight": 0.01059269905090332, "model.layers.20.mlp.gate_proj.weight": 0.0063842507295830304, "model.layers.20.mlp.up_proj.weight": 0.005228486171988554, "model.layers.20.mlp.down_proj.weight": 0.005610576895780341, "model.layers.20.input_layernorm.weight": 0.00341796875, "model.layers.20.post_attention_layernorm.weight": 0.0009765625, "model.layers.21.self_attn.q_proj.weight": 0.009576082229614258, "model.layers.21.self_attn.q_proj.bias": 0.0146484375, "model.layers.21.self_attn.k_proj.weight": 0.012851715087890625, "model.layers.21.self_attn.k_proj.bias": 0.01171875, "model.layers.21.self_attn.v_proj.weight": 0.005115509033203125, "model.layers.21.self_attn.v_proj.bias": 0.0078125, "model.layers.21.self_attn.o_proj.weight": 0.00723576545715332, "model.layers.21.mlp.gate_proj.weight": 0.006394630254701127, "model.layers.21.mlp.up_proj.weight": 0.00441129817519077, "model.layers.21.mlp.down_proj.weight": 0.004886937695880269, "model.layers.21.input_layernorm.weight": 0.0, "model.layers.21.post_attention_layernorm.weight": 0.00048828125, "model.layers.22.self_attn.q_proj.weight": 0.00997471809387207, "model.layers.22.self_attn.q_proj.bias": 0.02001953125, "model.layers.22.self_attn.k_proj.weight": 0.012315750122070312, "model.layers.22.self_attn.k_proj.bias": 0.02734375, "model.layers.22.self_attn.v_proj.weight": 0.0069980621337890625, "model.layers.22.self_attn.v_proj.bias": 0.015625, "model.layers.22.self_attn.o_proj.weight": 0.006277799606323242, "model.layers.22.mlp.gate_proj.weight": 0.005951282589934593, "model.layers.22.mlp.up_proj.weight": 0.00454915956009266, "model.layers.22.mlp.down_proj.weight": 0.004764024601426236, "model.layers.22.input_layernorm.weight": 0.00146484375, "model.layers.22.post_attention_layernorm.weight": 0.00048828125, "model.layers.23.self_attn.q_proj.weight": 0.01090860366821289, "model.layers.23.self_attn.q_proj.bias": 0.0234375, "model.layers.23.self_attn.k_proj.weight": 0.010976791381835938, "model.layers.23.self_attn.k_proj.bias": 0.01171875, "model.layers.23.self_attn.v_proj.weight": 0.0055103302001953125, "model.layers.23.self_attn.v_proj.bias": 0.01953125, "model.layers.23.self_attn.o_proj.weight": 0.0074884891510009766, "model.layers.23.mlp.gate_proj.weight": 0.0061828701995139896, "model.layers.23.mlp.up_proj.weight": 0.0050842373870139896, "model.layers.23.mlp.down_proj.weight": 0.005050171253293059, "model.layers.23.input_layernorm.weight": 0.00048828125, "model.layers.23.post_attention_layernorm.weight": 0.00048828125, "model.layers.24.self_attn.q_proj.weight": 0.008814096450805664, "model.layers.24.self_attn.q_proj.bias": 0.01220703125, "model.layers.24.self_attn.k_proj.weight": 0.008535385131835938, "model.layers.24.self_attn.k_proj.bias": 0.01953125, "model.layers.24.self_attn.v_proj.weight": 0.0046138763427734375, "model.layers.24.self_attn.v_proj.bias": 0.01171875, "model.layers.24.self_attn.o_proj.weight": 0.006539344787597656, "model.layers.24.mlp.gate_proj.weight": 0.006083466285882994, "model.layers.24.mlp.up_proj.weight": 0.004630421483239462, "model.layers.24.mlp.down_proj.weight": 0.00479276790175327, "model.layers.24.input_layernorm.weight": 0.0, "model.layers.24.post_attention_layernorm.weight": 0.0009765625, "model.layers.25.self_attn.q_proj.weight": 0.013570547103881836, "model.layers.25.self_attn.q_proj.bias": 0.02490234375, "model.layers.25.self_attn.k_proj.weight": 0.012598037719726562, "model.layers.25.self_attn.k_proj.bias": 0.015625, "model.layers.25.self_attn.v_proj.weight": 0.005214691162109375, "model.layers.25.self_attn.v_proj.bias": 0.01953125, "model.layers.25.self_attn.o_proj.weight": 0.008258819580078125, "model.layers.25.mlp.gate_proj.weight": 0.006400219229764716, "model.layers.25.mlp.up_proj.weight": 0.004794098610101744, "model.layers.25.mlp.down_proj.weight": 0.004949392274368641, "model.layers.25.input_layernorm.weight": 0.0009765625, "model.layers.25.post_attention_layernorm.weight": 0.0009765625, "model.layers.26.self_attn.q_proj.weight": 0.00908660888671875, "model.layers.26.self_attn.q_proj.bias": 0.01708984375, "model.layers.26.self_attn.k_proj.weight": 0.009037017822265625, "model.layers.26.self_attn.k_proj.bias": 0.015625, "model.layers.26.self_attn.v_proj.weight": 0.005889892578125, "model.layers.26.self_attn.v_proj.bias": 0.0078125, "model.layers.26.self_attn.o_proj.weight": 0.006587982177734375, "model.layers.26.mlp.gate_proj.weight": 0.006497316582258357, "model.layers.26.mlp.up_proj.weight": 0.0049158584239871, "model.layers.26.mlp.down_proj.weight": 0.0049183867698492, "model.layers.26.input_layernorm.weight": 0.00146484375, "model.layers.26.post_attention_layernorm.weight": 0.00048828125, "model.layers.27.self_attn.q_proj.weight": 0.011307477951049805, "model.layers.27.self_attn.q_proj.bias": 0.015625, "model.layers.27.self_attn.k_proj.weight": 0.011981964111328125, "model.layers.27.self_attn.k_proj.bias": 0.01953125, "model.layers.27.self_attn.v_proj.weight": 0.0067272186279296875, "model.layers.27.self_attn.v_proj.bias": 0.01171875, "model.layers.27.self_attn.o_proj.weight": 0.00846719741821289, "model.layers.27.mlp.gate_proj.weight": 0.006557553313499273, "model.layers.27.mlp.up_proj.weight": 0.004605138024618459, "model.layers.27.mlp.down_proj.weight": 0.004726853481558866, "model.layers.27.input_layernorm.weight": 0.04833984375, "model.layers.27.post_attention_layernorm.weight": 0.0029296875, "model.layers.28.self_attn.q_proj.weight": 0.010120868682861328, "model.layers.28.self_attn.q_proj.bias": 0.01708984375, "model.layers.28.self_attn.k_proj.weight": 0.0081787109375, "model.layers.28.self_attn.k_proj.bias": 0.03515625, "model.layers.28.self_attn.v_proj.weight": 0.008508682250976562, "model.layers.28.self_attn.v_proj.bias": 0.02734375, "model.layers.28.self_attn.o_proj.weight": 0.008358478546142578, "model.layers.28.mlp.gate_proj.weight": 0.005965343741483466, "model.layers.28.mlp.up_proj.weight": 0.004222958586936773, "model.layers.28.mlp.down_proj.weight": 0.004351904225903888, "model.layers.28.input_layernorm.weight": 0.044921875, "model.layers.28.post_attention_layernorm.weight": 0.0068359375, "model.layers.29.self_attn.q_proj.weight": 0.008140325546264648, "model.layers.29.self_attn.q_proj.bias": 0.01904296875, "model.layers.29.self_attn.k_proj.weight": 0.010297775268554688, "model.layers.29.self_attn.k_proj.bias": 0.0078125, "model.layers.29.self_attn.v_proj.weight": 0.0036525726318359375, "model.layers.29.self_attn.v_proj.bias": 0.015625, "model.layers.29.self_attn.o_proj.weight": 0.006406068801879883, "model.layers.29.mlp.gate_proj.weight": 0.005755224893259448, "model.layers.29.mlp.up_proj.weight": 0.0041372609692950585, "model.layers.29.mlp.down_proj.weight": 0.004430371661518895, "model.layers.29.input_layernorm.weight": 0.03369140625, "model.layers.29.post_attention_layernorm.weight": 0.0087890625, "model.layers.30.self_attn.q_proj.weight": 0.010857582092285156, "model.layers.30.self_attn.q_proj.bias": 0.0166015625, "model.layers.30.self_attn.k_proj.weight": 0.0092010498046875, "model.layers.30.self_attn.k_proj.bias": 0.0234375, "model.layers.30.self_attn.v_proj.weight": 0.008802413940429688, "model.layers.30.self_attn.v_proj.bias": 0.01171875, "model.layers.30.self_attn.o_proj.weight": 0.0076978206634521484, "model.layers.30.mlp.gate_proj.weight": 0.0060554770536200946, "model.layers.30.mlp.up_proj.weight": 0.0044899430385855746, "model.layers.30.mlp.down_proj.weight": 0.004863872084506723, "model.layers.30.input_layernorm.weight": 0.02685546875, "model.layers.30.post_attention_layernorm.weight": 0.00830078125, "model.layers.31.self_attn.q_proj.weight": 0.011382818222045898, "model.layers.31.self_attn.q_proj.bias": 0.01904296875, "model.layers.31.self_attn.k_proj.weight": 0.012683868408203125, "model.layers.31.self_attn.k_proj.bias": 0.015625, "model.layers.31.self_attn.v_proj.weight": 0.011198043823242188, "model.layers.31.self_attn.v_proj.bias": 0.00390625, "model.layers.31.self_attn.o_proj.weight": 0.010638713836669922, "model.layers.31.mlp.gate_proj.weight": 0.006080050801121911, "model.layers.31.mlp.up_proj.weight": 0.004796449528184048, "model.layers.31.mlp.down_proj.weight": 0.004905567612758902, "model.layers.31.input_layernorm.weight": 0.025390625, "model.layers.31.post_attention_layernorm.weight": 0.01171875, "model.layers.32.self_attn.q_proj.weight": 0.013468742370605469, "model.layers.32.self_attn.q_proj.bias": 0.0244140625, "model.layers.32.self_attn.k_proj.weight": 0.013580322265625, "model.layers.32.self_attn.k_proj.bias": 0.01953125, "model.layers.32.self_attn.v_proj.weight": 0.01422882080078125, "model.layers.32.self_attn.v_proj.bias": 0.00390625, "model.layers.32.self_attn.o_proj.weight": 0.005270957946777344, "model.layers.32.mlp.gate_proj.weight": 0.004860367885855741, "model.layers.32.mlp.up_proj.weight": 0.0038567920063817224, "model.layers.32.mlp.down_proj.weight": 0.004297788753065952, "model.layers.32.input_layernorm.weight": 0.0419921875, "model.layers.32.post_attention_layernorm.weight": 0.01611328125, "model.layers.33.self_attn.q_proj.weight": 0.013632774353027344, "model.layers.33.self_attn.q_proj.bias": 0.02880859375, "model.layers.33.self_attn.k_proj.weight": 0.01604461669921875, "model.layers.33.self_attn.k_proj.bias": 0.02734375, "model.layers.33.self_attn.v_proj.weight": 0.014108657836914062, "model.layers.33.self_attn.v_proj.bias": 0.0078125, "model.layers.33.self_attn.o_proj.weight": 0.004814863204956055, "model.layers.33.mlp.gate_proj.weight": 0.004432234653206759, "model.layers.33.mlp.up_proj.weight": 0.003917383593182231, "model.layers.33.mlp.down_proj.weight": 0.004009113755337027, "model.layers.33.input_layernorm.weight": 0.0361328125, "model.layers.33.post_attention_layernorm.weight": 0.02099609375, "model.layers.34.self_attn.q_proj.weight": 0.0071566104888916016, "model.layers.34.self_attn.q_proj.bias": 0.0234375, "model.layers.34.self_attn.k_proj.weight": 0.0068759918212890625, "model.layers.34.self_attn.k_proj.bias": 0.02734375, "model.layers.34.self_attn.v_proj.weight": 0.0054073333740234375, "model.layers.34.self_attn.v_proj.bias": 0.0078125, "model.layers.34.self_attn.o_proj.weight": 0.0051386356353759766, "model.layers.34.mlp.gate_proj.weight": 0.004111533941224564, "model.layers.34.mlp.up_proj.weight": 0.003487964009129724, "model.layers.34.mlp.down_proj.weight": 0.0037202169728833574, "model.layers.34.input_layernorm.weight": 0.017578125, "model.layers.34.post_attention_layernorm.weight": 0.01611328125, "model.layers.35.self_attn.q_proj.weight": 0.005122184753417969, "model.layers.35.self_attn.q_proj.bias": 0.0185546875, "model.layers.35.self_attn.k_proj.weight": 0.0061702728271484375, "model.layers.35.self_attn.k_proj.bias": 0.03515625, "model.layers.35.self_attn.v_proj.weight": 0.0050525665283203125, "model.layers.35.self_attn.v_proj.bias": 0.00390625, "model.layers.35.self_attn.o_proj.weight": 0.005282163619995117, "model.layers.35.mlp.gate_proj.weight": 0.004248907399732013, "model.layers.35.mlp.up_proj.weight": 0.004092238670171693, "model.layers.35.mlp.down_proj.weight": 0.0051018027372138446, "model.layers.35.input_layernorm.weight": 0.0185546875, "model.layers.35.post_attention_layernorm.weight": 0.0166015625, "model.norm.weight": 0.01611328125}